debugger.py
aigdb-0.1.0.dist-info/METADATA
aigdb-0.1.0.dist-info/WHEEL
aigdb-0.1.0.dist-info/top_level.txt
aigdb-0.1.0.dist-info/RECORD
